polysolve/__init__.py
polysolve-0.7.0.dist-info/licenses/LICENSE
polysolve-0.7.0.dist-info/METADATA
polysolve-0.7.0.dist-info/WHEEL
polysolve-0.7.0.dist-info/top_level.txt
polysolve-0.7.0.dist-info/RECORD
