Metadata-Version: 2.4
Name: polysolve
Version: 0.7.0
Summary: A Python library for representing, manipulating, and solving exponential functions using analytical methods and genetic algorithms, with optional CUDA acceleration.
Author-email: Jonathan Rampersad <jonathan@jono-rams.work>
License: MIT License
Project-URL: Homepage, https://polysolve.jono-rams.work
Project-URL: Documentation, https://polysolve.jono-rams.work/docs
Project-URL: Repository, https://github.com/jono-rams/PolySolve
Project-URL: Bug Tracker, https://github.com/jono-rams/PolySolve/issues
Keywords: math,polynomial,genetic algorithm,cuda,equation solver
Classifier: Development Status :: 4 - Beta
Classifier: Intended Audience :: Developers
Classifier: Intended Audience :: Science/Research
Classifier: License :: OSI Approved :: MIT License
Classifier: Operating System :: OS Independent
Classifier: Programming Language :: Python :: 3
Classifier: Programming Language :: Python :: 3.8
Classifier: Programming Language :: Python :: 3.9
Classifier: Programming Language :: Python :: 3.10
Classifier: Programming Language :: Python :: 3.11
Classifier: Programming Language :: Python :: 3.12
Classifier: Topic :: Scientific/Engineering :: Mathematics
Requires-Python: >=3.8
License-File: LICENSE
Requires-Dist: numpy>=1.21
Requires-Dist: numba
Provides-Extra: cuda12
Requires-Dist: cupy-cuda12x; extra == "cuda12"
Provides-Extra: dev
Requires-Dist: pytest; extra == "dev"
Dynamic: license-file
